[
  {
    "stage": "nlink_3_warm",
    "n_poles": 3,
    "mode": "recon_fast_bandit",
    "train_episodes_budget": 500,
    "gain_trials": 6,
    "trial_train_episodes": 83,
    "eval_episodes": 50,
    "best_score": 279.645,
    "best_trial": {
      "trial": 0,
      "score": 279.645,
      "train_steps": {
        "mean": 493.28915662650604,
        "median": 500.0,
        "p10": 500.0,
        "p90": 500.0,
        "max": 500.0
      },
      "eval_steps": {
        "mean": 235.42,
        "median": 223.0,
        "p10": 176.9,
        "p90": 294.8,
        "max": 415.0
      },
      "gains": {
        "angle_gain": 18.0,
        "velocity_gain": 3.8,
        "cart_position_gain": 0.75,
        "cart_velocity_gain": 0.25,
        "worst_velocity_mix": 0.3,
        "base_velocity_mix": 0.35,
        "outer_link_weight": 0.25,
        "center_confidence": 0.45,
        "chain_confidence": 0.65,
        "recover_confidence": 0.85
      }
    },
    "passed": true,
    "bandit": {
      "select_control_regime": {
        "avoid_rail": {
          "pulls": 6841,
          "mean_reward": -0.0002,
          "last_reward": -0.0526
        },
        "damp_energy": {
          "pulls": 6772,
          "mean_reward": -0.0004,
          "last_reward": 0.0432
        },
        "recover_worst_pole": {
          "pulls": 6843,
          "mean_reward": -0.0001,
          "last_reward": -0.0506
        },
        "recover_base_pole": {
          "pulls": 6820,
          "mean_reward": -0.0002,
          "last_reward": -0.0353
        },
        "stabilize_chain": {
          "pulls": 6836,
          "mean_reward": -0.0002,
          "last_reward": -0.0328
        },
        "center_cart": {
          "pulls": 6831,
          "mean_reward": -0.0002,
          "last_reward": -0.0497
        }
      }
    },
    "trace_steps": 225,
    "trace_return": 224.0,
    "best_gains": {
      "angle_gain": 18.0,
      "velocity_gain": 3.8,
      "cart_position_gain": 0.75,
      "cart_velocity_gain": 0.25,
      "worst_velocity_mix": 0.3,
      "base_velocity_mix": 0.35,
      "outer_link_weight": 0.25,
      "center_confidence": 0.45,
      "chain_confidence": 0.65,
      "recover_confidence": 0.85
    },
    "trials": [
      {
        "trial": 0,
        "score": 279.645,
        "train_steps": {
          "mean": 493.28915662650604,
          "median": 500.0,
          "p10": 500.0,
          "p90": 500.0,
          "max": 500.0
        },
        "eval_steps": {
          "mean": 235.42,
          "median": 223.0,
          "p10": 176.9,
          "p90": 294.8,
          "max": 415.0
        },
        "gains": {
          "angle_gain": 18.0,
          "velocity_gain": 3.8,
          "cart_position_gain": 0.75,
          "cart_velocity_gain": 0.25,
          "worst_velocity_mix": 0.3,
          "base_velocity_mix": 0.35,
          "outer_link_weight": 0.25,
          "center_confidence": 0.45,
          "chain_confidence": 0.65,
          "recover_confidence": 0.85
        }
      }
    ],
    "report_dir": "reports/curriculum_n3_solved/00_nlink_3_warm"
  },
  {
    "stage": "nlink_3_stable",
    "n_poles": 3,
    "mode": "recon_fast_bandit",
    "train_episodes_budget": 2000,
    "gain_trials": 20,
    "trial_train_episodes": 100,
    "eval_episodes": 100,
    "best_score": 675.0,
    "best_trial": {
      "trial": 1,
      "score": 675.0,
      "train_steps": {
        "mean": 439.64,
        "median": 500.0,
        "p10": 279.2,
        "p90": 500.0,
        "max": 500.0
      },
      "eval_steps": {
        "mean": 500.0,
        "median": 500.0,
        "p10": 500.0,
        "p90": 500.0,
        "max": 500.0
      },
      "gains": {
        "angle_gain": 17.189750516135053,
        "velocity_gain": 4.166426604187394,
        "cart_position_gain": 0.720089778695599,
        "cart_velocity_gain": 0.2362164632600696,
        "worst_velocity_mix": 0.25375752888487496,
        "base_velocity_mix": 0.3368166792809546,
        "outer_link_weight": 0.30539500786711565,
        "center_confidence": 0.48570137771688016,
        "chain_confidence": 0.7833742859892516,
        "recover_confidence": 0.888948088316412
      }
    },
    "passed": true,
    "bandit": {
      "select_control_regime": {
        "avoid_rail": {
          "pulls": 7363,
          "mean_reward": -0.0017,
          "last_reward": -0.0527
        },
        "damp_energy": {
          "pulls": 7386,
          "mean_reward": -0.0016,
          "last_reward": -0.0564
        },
        "recover_worst_pole": {
          "pulls": 7381,
          "mean_reward": -0.0017,
          "last_reward": -0.0507
        },
        "recover_base_pole": {
          "pulls": 7306,
          "mean_reward": -0.0019,
          "last_reward": -0.056
        },
        "stabilize_chain": {
          "pulls": 7230,
          "mean_reward": -0.0022,
          "last_reward": 0.0416
        },
        "center_cart": {
          "pulls": 7298,
          "mean_reward": -0.002,
          "last_reward": -0.057
        }
      }
    },
    "trace_steps": 500,
    "trace_return": 500.0,
    "best_gains": {
      "angle_gain": 17.189750516135053,
      "velocity_gain": 4.166426604187394,
      "cart_position_gain": 0.720089778695599,
      "cart_velocity_gain": 0.2362164632600696,
      "worst_velocity_mix": 0.25375752888487496,
      "base_velocity_mix": 0.3368166792809546,
      "outer_link_weight": 0.30539500786711565,
      "center_confidence": 0.48570137771688016,
      "chain_confidence": 0.7833742859892516,
      "recover_confidence": 0.888948088316412
    },
    "trials": [
      {
        "trial": 0,
        "score": 267.795,
        "train_steps": {
          "mean": 433.06,
          "median": 500.0,
          "p10": 253.5,
          "p90": 500.0,
          "max": 500.0
        },
        "eval_steps": {
          "mean": 226.57,
          "median": 196.0,
          "p10": 162.9,
          "p90": 338.5000000000001,
          "max": 500.0
        },
        "gains": {
          "angle_gain": 18.0,
          "velocity_gain": 3.8,
          "cart_position_gain": 0.75,
          "cart_velocity_gain": 0.25,
          "worst_velocity_mix": 0.3,
          "base_velocity_mix": 0.35,
          "outer_link_weight": 0.25,
          "center_confidence": 0.45,
          "chain_confidence": 0.65,
          "recover_confidence": 0.85
        }
      },
      {
        "trial": 1,
        "score": 675.0,
        "train_steps": {
          "mean": 439.64,
          "median": 500.0,
          "p10": 279.2,
          "p90": 500.0,
          "max": 500.0
        },
        "eval_steps": {
          "mean": 500.0,
          "median": 500.0,
          "p10": 500.0,
          "p90": 500.0,
          "max": 500.0
        },
        "gains": {
          "angle_gain": 17.189750516135053,
          "velocity_gain": 4.166426604187394,
          "cart_position_gain": 0.720089778695599,
          "cart_velocity_gain": 0.2362164632600696,
          "worst_velocity_mix": 0.25375752888487496,
          "base_velocity_mix": 0.3368166792809546,
          "outer_link_weight": 0.30539500786711565,
          "center_confidence": 0.48570137771688016,
          "chain_confidence": 0.7833742859892516,
          "recover_confidence": 0.888948088316412
        }
      }
    ],
    "report_dir": "reports/curriculum_n3_solved/01_nlink_3_stable"
  },
  {
    "stage": "nlink_3_robust",
    "n_poles": 3,
    "mode": "recon_fast_bandit",
    "train_episodes_budget": 5000,
    "gain_trials": 30,
    "trial_train_episodes": 166,
    "eval_episodes": 100,
    "best_score": 673.5,
    "best_trial": {
      "trial": 1,
      "score": 673.5,
      "train_steps": {
        "mean": 393.4698795180723,
        "median": 411.5,
        "p10": 224.0,
        "p90": 500.0,
        "max": 500.0
      },
      "eval_steps": {
        "mean": 499.0,
        "median": 500.0,
        "p10": 500.0,
        "p90": 500.0,
        "max": 500.0
      },
      "gains": {
        "angle_gain": 18.455673688524463,
        "velocity_gain": 4.307757804880502,
        "cart_position_gain": 0.5335136426077935,
        "cart_velocity_gain": 0.2755292452234538,
        "worst_velocity_mix": 0.2779742469861586,
        "base_velocity_mix": 0.3684577499128183,
        "outer_link_weight": 0.22523863205871322,
        "center_confidence": 0.3548496308946019,
        "chain_confidence": 0.6674602480544694,
        "recover_confidence": 0.8171026837215034
      }
    },
    "passed": true,
    "bandit": {
      "select_control_regime": {
        "avoid_rail": {
          "pulls": 1434,
          "mean_reward": -0.1155,
          "last_reward": -2.2037
        },
        "damp_energy": {
          "pulls": 12839,
          "mean_reward": -0.0019,
          "last_reward": -0.025
        },
        "recover_worst_pole": {
          "pulls": 12843,
          "mean_reward": -0.0019,
          "last_reward": -0.0289
        },
        "recover_base_pole": {
          "pulls": 12784,
          "mean_reward": -0.002,
          "last_reward": -0.0346
        },
        "stabilize_chain": {
          "pulls": 12886,
          "mean_reward": -0.0018,
          "last_reward": -0.0312
        },
        "center_cart": {
          "pulls": 12530,
          "mean_reward": -0.0025,
          "last_reward": -0.1646
        }
      }
    },
    "trace_steps": 500,
    "trace_return": 500.0,
    "best_gains": {
      "angle_gain": 18.455673688524463,
      "velocity_gain": 4.307757804880502,
      "cart_position_gain": 0.5335136426077935,
      "cart_velocity_gain": 0.2755292452234538,
      "worst_velocity_mix": 0.2779742469861586,
      "base_velocity_mix": 0.3684577499128183,
      "outer_link_weight": 0.22523863205871322,
      "center_confidence": 0.3548496308946019,
      "chain_confidence": 0.6674602480544694,
      "recover_confidence": 0.8171026837215034
    },
    "trials": [
      {
        "trial": 0,
        "score": 518.26,
        "train_steps": {
          "mean": 376.7831325301205,
          "median": 377.5,
          "p10": 193.0,
          "p90": 500.0,
          "max": 500.0
        },
        "eval_steps": {
          "mean": 448.06,
          "median": 500.0,
          "p10": 108.80000000000001,
          "p90": 500.0,
          "max": 500.0
        },
        "gains": {
          "angle_gain": 17.189750516135053,
          "velocity_gain": 4.166426604187394,
          "cart_position_gain": 0.720089778695599,
          "cart_velocity_gain": 0.2362164632600696,
          "worst_velocity_mix": 0.25375752888487496,
          "base_velocity_mix": 0.3368166792809546,
          "outer_link_weight": 0.30539500786711565,
          "center_confidence": 0.48570137771688016,
          "chain_confidence": 0.7833742859892516,
          "recover_confidence": 0.888948088316412
        }
      },
      {
        "trial": 1,
        "score": 673.5,
        "train_steps": {
          "mean": 393.4698795180723,
          "median": 411.5,
          "p10": 224.0,
          "p90": 500.0,
          "max": 500.0
        },
        "eval_steps": {
          "mean": 499.0,
          "median": 500.0,
          "p10": 500.0,
          "p90": 500.0,
          "max": 500.0
        },
        "gains": {
          "angle_gain": 18.455673688524463,
          "velocity_gain": 4.307757804880502,
          "cart_position_gain": 0.5335136426077935,
          "cart_velocity_gain": 0.2755292452234538,
          "worst_velocity_mix": 0.2779742469861586,
          "base_velocity_mix": 0.3684577499128183,
          "outer_link_weight": 0.22523863205871322,
          "center_confidence": 0.3548496308946019,
          "chain_confidence": 0.6674602480544694,
          "recover_confidence": 0.8171026837215034
        }
      }
    ],
    "report_dir": "reports/curriculum_n3_solved/02_nlink_3_robust"
  }
]