{
  "candidate_id": "fa12e6c1dbe5",
  "checkpoint_path": "reports/n4_mingru_balanced_capacity_screen_20260613_seed9087/candidate_03_fa12e6c1dbe5/mingru_terminal.pt",
  "hidden_size": 256,
  "sequence_length": 32,
  "pure_mingru_policy": {
    "mean_survival": 461.6,
    "p10_survival": 396.9,
    "success_rate": 0.4,
    "max_survival": 500.0,
    "returns_mean": 461.0,
    "episodes": 40
  },
  "recon_mingru_terminal": {
    "mean_survival": 461.6,
    "p10_survival": 396.9,
    "success_rate": 0.4,
    "max_survival": 500.0,
    "returns_mean": 461.0,
    "episodes": 40
  },
  "kept": false,
  "mechanisms": {
    "minGRU_terminal": true,
    "pure_policy_baseline": true,
    "feedforward_policy_terminal": false,
    "edge_plasticity": false,
    "bandit_persistence": false,
    "slow_consolidation": false,
    "gain_mutation": false
  }
}